setup.py
c/cbor.h
c/cbormodule.c
cbor/__init__.py
cbor/cbor.py
cbor/cbor_rpc_client.py
cbor/tagmap.py
cbor.egg-info/PKG-INFO
cbor.egg-info/SOURCES.txt
cbor.egg-info/dependency_links.txt
cbor.egg-info/top_level.txt