Metadata-Version: 1.1
Name: cbor
Version: 0.1.20
Summary: RFC 7049 - Concise Binary Object Representation
Home-page: https://code.google.com/p/cbor
Author: Brian Olson
Author-email: bolson@bolson.org
License: Apache
Platform: UNKNOWN
Classifier: Development Status :: 4 - Beta
Classifier: Intended Audience :: Developers
Classifier: License :: OSI Approved :: Apache Software License
Classifier: Operating System :: OS Independent
Classifier: Programming Language :: Python :: 2.7
Classifier: Programming Language :: Python :: 3.3
Classifier: Programming Language :: Python :: 3.4
Classifier: Programming Language :: C
Classifier: Topic :: Software Development :: Libraries :: Python Modules
